Metadata-Version: 1.0
Name: spark-vio-evaluation
Version: 0.2
Summary: Code for evaluating the performance of the SPARK VIO pipeline
Home-page: https://github.com/ToniRV/spark_vio_evaluation
Author: Antoni Rosinol
Author-email: arosinol@mit.edu
License: MIT
Platform: UNKNOWN
